randdist/__init__.py
randdist/generate.py
randdist/test_randdist.py
RandDist-0.0.6.dist-info/LICENSE
RandDist-0.0.6.dist-info/METADATA
RandDist-0.0.6.dist-info/WHEEL
RandDist-0.0.6.dist-info/top_level.txt
RandDist-0.0.6.dist-info/RECORD
