Metadata-Version: 2.1
Name: RandDist
Version: 0.0.6
Summary: A random number generator with custom probability distribution function
Home-page: https://github.com/BehrouzSohrabi/RandDist
Author: Behrouz Sohrabi
Author-email: sohrabi.beh@gmail.com
License: UNKNOWN
Project-URL: Bug Tracker, https://github.com/BehrouzSohrabi/RandDist/issues
Platform: UNKNOWN
Classifier: Programming Language :: Python :: 3
Classifier: License :: OSI Approved :: MIT License
Classifier: Operating System :: OS Independent
Requires-Python: >=3.6
License-File: LICENSE
